README.md
setup.py
pyfindtext/__init__.py
pyfindtext/find.py
pyfindtext.egg-info/PKG-INFO
pyfindtext.egg-info/SOURCES.txt
pyfindtext.egg-info/dependency_links.txt
pyfindtext.egg-info/top_level.txt