Metadata-Version: 1.0
Name: pyfindtext
Version: 0.0.1
Summary: Find text in files
Home-page: https://github.com/lagliam/pyfindtext
Author: Liam Goring
Author-email: UNKNOWN
License: GNU General Public License v3.0
Platform: UNKNOWN
